smoltoken-0.1.4.dist-info/RECORD
smoltoken-0.1.4.dist-info/WHEEL
smoltoken-0.1.4.dist-info/METADATA
smoltoken-0.1.4.dist-info/licenses/LICENSE
smoltoken/__init__.py
smoltoken/core.py
smoltoken/_smoltoken.cpython-312-darwin.so
smoltoken/py.typed
