Metadata-Version: 2.4
Name: smoltoken
Version: 0.1.4
Classifier: Development Status :: 3 - Alpha
Classifier: Intended Audience :: Developers
Classifier: Topic :: Software Development :: Build Tools
License-File: LICENSE
Summary: A light-weight & fast library for Byte Pair Encoding (BPE) tokenization.
Keywords: tokenizer,bpe,ai
Author-email: Arun S V <svarunid@gmail.com>
Requires-Python: >=3.11
Project-URL: repository, https://github.com/svarunid/smoltoken
